tumbleoffgrid/__init__.py
tumbleoffgrid-1.2.0.dist-info/LICENSE.txt
tumbleoffgrid-1.2.0.dist-info/METADATA
tumbleoffgrid-1.2.0.dist-info/WHEEL
tumbleoffgrid-1.2.0.dist-info/entry_points.txt
tumbleoffgrid-1.2.0.dist-info/top_level.txt
tumbleoffgrid-1.2.0.dist-info/RECORD
