Metadata-Version: 2.1
Name: tumbleoffgrid
Version: 1.2.0
Summary: View your exported tumblr offline. Collaborate.
Home-page: https://github.com/pypa/sampleproject
Author: The Python Packaging Authority
Author-email: 
License: UNKNOWN
Project-URL: Say Thanks!, http://saythanks.io/to/example
Project-URL: Funding, https://donate.pypi.org
Project-URL: Bug Reports, https://example.com
Project-URL: Source, https://github.com/pypa/sampleproject/
Keywords: sample setuptools development
Platform: UNKNOWN
Classifier: Development Status :: 3 - Alpha
Classifier: Intended Audience :: Developers
Classifier: Topic :: Software Development :: Build Tools
Classifier: License :: OSI Approved :: MIT License
Classifier: Programming Language :: Python :: 3
Classifier: Programming Language :: Python :: 3.4
Classifier: Programming Language :: Python :: 3.5
Classifier: Programming Language :: Python :: 3.6
Classifier: Programming Language :: Python :: 3.7
Provides-Extra: dev
Requires-Dist: check-manifest ; extra == 'dev'
Provides-Extra: test
Requires-Dist: coverage ; extra == 'test'
